PFERD/__init__.py
PFERD/__main__.py
PFERD/config.py
PFERD/deduplicator.py
PFERD/limiter.py
PFERD/logging.py
PFERD/output_dir.py
PFERD/pferd.py
PFERD/report.py
PFERD/transformer.py
PFERD/utils.py
PFERD/version.py
PFERD/auth/__init__.py
PFERD/auth/authenticator.py
PFERD/auth/credential_file.py
PFERD/auth/keyring.py
PFERD/auth/pass_.py
PFERD/auth/simple.py
PFERD/auth/tfa.py
PFERD/cli/__init__.py
PFERD/cli/command_ilias_web.py
PFERD/cli/command_kit_ilias_web.py
PFERD/cli/command_kit_ipd.py
PFERD/cli/command_local.py
PFERD/cli/common_ilias_args.py
PFERD/cli/parser.py
PFERD/crawl/__init__.py
PFERD/crawl/crawler.py
PFERD/crawl/http_crawler.py
PFERD/crawl/kit_ipd_crawler.py
PFERD/crawl/local_crawler.py
PFERD/crawl/ilias/__init__.py
PFERD/crawl/ilias/async_helper.py
PFERD/crawl/ilias/file_templates.py
PFERD/crawl/ilias/ilias_html_cleaner.py
PFERD/crawl/ilias/ilias_web_crawler.py
PFERD/crawl/ilias/kit_ilias_html.py
PFERD/crawl/ilias/kit_ilias_web_crawler.py
PFERD/crawl/ilias/shibboleth_login.py
pferd-3.8.3.dist-info/licenses/LICENSE
pferd-3.8.3.dist-info/METADATA
pferd-3.8.3.dist-info/WHEEL
pferd-3.8.3.dist-info/entry_points.txt
pferd-3.8.3.dist-info/top_level.txt
pferd-3.8.3.dist-info/RECORD
