Metadata-Version: 2.4
Name: PFERD
Version: 3.8.3
Requires-Python: >=3.11
License-File: LICENSE
Requires-Dist: aiohttp>=3.8.1
Requires-Dist: beautifulsoup4>=4.10.0
Requires-Dist: rich>=11.0.0
Requires-Dist: keyring>=23.5.0
Requires-Dist: certifi>=2021.10.8
Dynamic: license-file
